main.py
wei516_ppa-0.1.3.dist-info/METADATA
wei516_ppa-0.1.3.dist-info/WHEEL
wei516_ppa-0.1.3.dist-info/entry_points.txt
wei516_ppa-0.1.3.dist-info/top_level.txt
wei516_ppa-0.1.3.dist-info/RECORD
