Metadata-Version: 2.4
Name: wei516-ppa
Version: 0.1.3
Summary: ppa test
Requires-Python: >=3.13
Requires-Dist: httpx>=0.28.1
Requires-Dist: mcp>=1.20.0
